{
  "resourceType": "DocumentReference",
  "id": "nzf-pil-paracetamol",
  "meta": {
    "lastUpdated": "2026-05-18T00:00:00Z"
  },
  "status": "current",
  "type": {
    "coding": [
      {
        "system": "https://standards.digital.health.nz/ns/nzf-document-type-code",
        "code": "PIL"
      }
    ]
  },
  "content": [
    {
      "attachment": {
        "extension": [
          {
            "url": "http://hl7.org.nz/fhir/StructureDefinition/nzf-page-size",
            "valueCodeableConcept": {
              "coding": [
                {
                  "system": "https://standards.digital.health.nz/ns/nzf-page-size-code",
                  "code": "A4",
                  "display": "A4"
                }
              ],
              "text": "A4"
            }
          }
        ],
        "contentType": "application/pdf",
        "language": "en-NZ",
        "url": "http://www.mymedicines.nz/home/sheet/Paracetamol?format=pdfA4&inline=true",
        "title": "Paracetamol"
      }
    },
    {
      "attachment": {
        "extension": [
          {
            "url": "http://hl7.org.nz/fhir/StructureDefinition/nzf-page-size",
            "valueCodeableConcept": {
              "coding": [
                {
                  "system": "https://standards.digital.health.nz/ns/nzf-page-size-code",
                  "code": "A4",
                  "display": "A4"
                }
              ],
              "text": "A4"
            }
          }
        ],
        "contentType": "application/pdf",
        "language": "mi",
        "url": "https://mymedicines.nz/TeReo/NZF/Paracetamol.pdf",
        "title": "Paracetamol"
      }
    }
  ],
  "context": {
    "extension": [
      {
        "url": "http://hl7.org.nz/fhir/StructureDefinition/nzf-pil-source",
        "valueCodeableConcept": {
          "text": "MyMedicine"
        }
      },
      {
        "url": "http://hl7.org.nz/fhir/StructureDefinition/nzf-pil-formulary",
        "valueCodeableConcept": {
          "text": "NZF"
        }
      }
    ]
  }
}